README.rst
setup.py
django_easy.egg-info/PKG-INFO
django_easy.egg-info/SOURCES.txt
django_easy.egg-info/dependency_links.txt
django_easy.egg-info/top_level.txt
easy/__init__.py
easy/decorators.py